zw_fast_quantile_py-0.2.0.dist-info/METADATA
zw_fast_quantile_py-0.2.0.dist-info/WHEEL
zw_fast_quantile_py/__init__.py
zw_fast_quantile_py/zw_fast_quantile_py.cpython-39-darwin.so
zw_fast_quantile_py-0.2.0.dist-info/RECORD
